discer/__init__.py
discer/grouping.py
discer/ordering.py
discer/relations.py
discr-0.1.0.dist-info/LICENSE
discr-0.1.0.dist-info/METADATA
discr-0.1.0.dist-info/WHEEL
discr-0.1.0.dist-info/top_level.txt
discr-0.1.0.dist-info/RECORD
